pkglib35/__init__.py
pkglib35/mod_a.py
pkglib35/mod_b.py
pkglib35-1.0.0.dist-info/METADATA
pkglib35-1.0.0.dist-info/WHEEL
pkglib35-1.0.0.dist-info/top_level.txt
pkglib35-1.0.0.dist-info/RECORD
