Metadata-Version: 2.1
Name: pkglib35
Version: 1.0.0
Summary: A description of your package
Home-page: https://example.com
Author: Your Name
Author-email: your@email.com
